repoze.retry-2.1-py3.12-nspkg.pth
repoze/retry/__init__.py
repoze/retry/tests.py
repoze.retry-2.1.dist-info/LICENSE.txt
repoze.retry-2.1.dist-info/METADATA
repoze.retry-2.1.dist-info/WHEEL
repoze.retry-2.1.dist-info/entry_points.txt
repoze.retry-2.1.dist-info/namespace_packages.txt
repoze.retry-2.1.dist-info/top_level.txt
repoze.retry-2.1.dist-info/RECORD
